mptradelib/__init__.py
mptradelib/backtest.py
mptradelib/broker/__init__.py
mptradelib/broker/broker.py
mptradelib/broker/session.py
mptradelib/broker/shoonya.py
mptradelib/broker/ticker.py
mptradelib/cli/__init__.py
mptradelib/cli/new.py
mptradelib/cli/templates/strategy/__init__.py.jinja
mptradelib/cli/templates/strategy/backtest.ipynb.jinja
mptradelib/cli/templates/strategy/funcs.py.jinja
mptradelib/cli/templates/strategy/livetrade.py.jinja
mptradelib/feed.py
mptradelib/livetrade.py
mptradelib/optimizers/__init__.py
mptradelib/optimizers/walkforward.py
mptradelib/test_renko.py
mptradelib/utils/__init__.py
mptradelib/utils/chart.py
mptradelib/utils/downloader.py
mptradelib/utils/simulated_trades.py
mptradelib/utils/tearsheet.py
mptradelib/utils/utils.py
mptradelib/widgets/__init__.py
mptradelib/widgets/daterangepicker.py
mptradelib-0.5.11.dist-info/METADATA
mptradelib-0.5.11.dist-info/WHEEL
mptradelib-0.5.11.dist-info/entry_points.txt
mptradelib-0.5.11.dist-info/RECORD
