Metadata-Version: 2.1
Name: mptradelib
Version: 0.5.11
Summary: 
Author: Abhilash Nanda
Author-email: wishabhilash@gmail.com
Requires-Python: >=3.10,<4.0
Classifier: Programming Language :: Python :: 3
Classifier: Programming Language :: Python :: 3.10
Classifier: Programming Language :: Python :: 3.11
Classifier: Programming Language :: Python :: 3.12
Provides-Extra: hyperopt
Provides-Extra: pandas
Provides-Extra: pandasta
Requires-Dist: click (>=8.1.7,<9.0.0)
Requires-Dist: fyers-apiv3 (==3.0.6)
Requires-Dist: jinja2 (>=3.1.3,<4.0.0)
Requires-Dist: jinja2-strcase (>=0.0.2,<0.0.3)
Requires-Dist: pydantic (==2.7.1)
Requires-Dist: pyotp (==2.9.0)
Requires-Dist: redis (>=5.0.4,<6.0.0)
Requires-Dist: requests (==2.31.0)
Requires-Dist: retry (==0.9.2)
Requires-Dist: tqdm (>=4.66.4,<5.0.0)
